alloniarest/__init__.py
alloniarest/auth.py
alloniarest/base.py
alloniarest/client.py
alloniarest/external_api_keys.py
alloniarest/signatures/__init__.py
alloniarest/signatures/sign_request.py
alloniarest/signatures/signature_base.py
alloniarest/signatures/signature_builder.py
alloniarest/signatures/signature_utils.py
alloniarest-1.3.0.dist-info/METADATA
alloniarest-1.3.0.dist-info/WHEEL
alloniarest-1.3.0.dist-info/RECORD
