Metadata-Version: 2.1
Name: alloniarest
Version: 1.3.0
Summary: Library to interact with AllOnIA's API
Author: ALLONIA
Requires-Python: >=3.9,<4.0
Classifier: Programming Language :: Python :: 3
Classifier: Programming Language :: Python :: 3.9
Classifier: Programming Language :: Python :: 3.10
Classifier: Programming Language :: Python :: 3.11
Classifier: Programming Language :: Python :: 3.12
Requires-Dist: alloniaconfigs (>=1.1.2,<2.0.0)
Requires-Dist: werkzeug (>=3.0.4,<4.0.0)
